ClientAgreement-Api/__init__.py
ClientAgreement-Api/app.py
ClientAgreement-Api/conftest.py
ClientAgreement-Api/create_db.py
ClientAgreement-Api/validators.py
ClientAgreement-Api/controllers/__init__.py
ClientAgreement-Api/controllers/agreement_controller.py
ClientAgreement-Api/controllers/user_controller.py
ClientAgreement-Api/models/__init__.py
ClientAgreement-Api/models/agreement.py
ClientAgreement-Api/models/user.py
ClientAgreement-Api/models/utils.py
ClientAgreement-Api/test/__init__.py
ClientAgreement-Api/test/controllers/__init__.py
ClientAgreement-Api/test/controllers/test_agreement_controllers.py
ClientAgreement-Api/test/controllers/test_user_controllers.py
client_agreement_api/__init__.py
client_agreement_api/app.py
client_agreement_api/conftest.py
client_agreement_api/create_db.py
client_agreement_api/validators.py
client_agreement_api/controllers/__init__.py
client_agreement_api/controllers/agreement_controller.py
client_agreement_api/controllers/user_controller.py
client_agreement_api/models/__init__.py
client_agreement_api/models/agreement.py
client_agreement_api/models/user.py
client_agreement_api/models/utils.py
client_agreement_api/openapi/__init__.py
client_agreement_api/openapi/specification.yaml
client_agreement_api/openapi/test_module.py
client_agreement_api/test/__init__.py
client_agreement_api/test/controllers/__init__.py
client_agreement_api/test/controllers/test_agreement_controllers.py
client_agreement_api/test/controllers/test_user_controllers.py
client_agreement_api-0.0.8.dist-info/LICENSE
client_agreement_api-0.0.8.dist-info/METADATA
client_agreement_api-0.0.8.dist-info/WHEEL
client_agreement_api-0.0.8.dist-info/top_level.txt
client_agreement_api-0.0.8.dist-info/RECORD
